llm4lint/__init__.py
llm4lint/augdata.py
llm4lint/augmentation.py
llm4lint/genlabels.py
llm4lint/linter.py
llm4lint/llm.py
llm4lint/llm4lint.py
llm4lint/randomdata.py
llm4lint/stackv2.py
llm4lint/train.py
llm4lint-0.1.0.dist-info/METADATA
llm4lint-0.1.0.dist-info/WHEEL
llm4lint-0.1.0.dist-info/entry_points.txt
llm4lint-0.1.0.dist-info/licenses/LICENSE
llm4lint-0.1.0.dist-info/RECORD
