Metadata-Version: 2.4
Name: llm4lint
Version: 0.1.0
Summary: A Linter that uses LLM to analyze code
Project-URL: Homepage, https://github.com/ahmedhus22/llm4lint
Project-URL: Issues, https://github.com/ahmedhus22/llm4lint/issues
Author-email: Syed Ahmed Hussain <ahmedhus22@gmail.com>
License-File: LICENSE
Classifier: License :: OSI Approved :: MIT License
Classifier: Programming Language :: Python :: 3
Requires-Python: >=3.10
Requires-Dist: ollama
